[{"feature_words": ["\u63a2\u5075", "\u30e9\u30d6\u30ec\u30bf\u30fc", "\u5834\u9762", "\u5287\u5834", "\u604b\u6b4c", "21", "\u6620\u753b", "\u30ad\u30e3\u30e9\u30af\u30bf\u30fc", "\u898b\u9003\u3057", "\u30b3\u30ca\u30f3"], "nega_count": 38, "posi_count": 338, "tweets_count": 2400, "retweets_count": 1620, "date": "2017/04/15"}, {"feature_words": ["21", "\u5730\u4e0a\u6ce2", "\u30c8\u30ea\u30aa", "\u89e3\u653e", "\u9ebb\u53cb", "\u6e21\u8fba", "\u3042\u3084\u3075\u3084", "\u6587\u53e5", "48", "\u9078\u6319"], "nega_count": 50, "posi_count": 380, "tweets_count": 2243, "retweets_count": 1414, "date": "2017/04/14"}, {"feature_words": ["\u5348\u5f8c", "\u5009\u5eab", "\u79e9\u7236\u9244\u9053", "\u30a2\u30fc\u30b1\u30fc\u30c9", "\u535a\u7269\u9928", "\u5165\u5834", "5000", "\u6642\u534a", "\u89e3\u653e", "\u6587\u53e5"], "nega_count": 49, "posi_count": 383, "tweets_count": 2175, "retweets_count": 1355, "date": "2017/04/13"}, {"feature_words": ["5000", "\u57fa\u88d5", "\u592a\u7530", "\u6749\u6c5f", "\u65b9\u773c", "\u4f5c\u8005", "\u3042\u304d", "\u5927\u5fd7", "\u30dd\u30b9\u30ab\u30b5\u30a4\u30ba", "\u512a\u5f85"], "nega_count": 65, "posi_count": 387, "tweets_count": 2442, "retweets_count": 1559, "date": "2017/04/12"}, {"feature_words": ["\u30bb\u30d6\u30a4\u30f3\u30a4\u30ec\u30d6\u30f3", "\u53d7\u53d6", "\u4f5c\u8005", "\u3042\u304d", "\u30e8\u30b3", "\u30bf\u30c6", "\u30b9\u30bf\u30fc\u30c8", "\u5165\u91d1", "\u6c7a\u5b9a", "\u5ca1\u5c71"], "nega_count": 55, "posi_count": 374, "tweets_count": 2710, "retweets_count": 1762, "date": "2017/04/11"}, {"feature_words": ["\u6d41\u661f", "\u30df\u30cb\u30d5\u30a9\u30c8\u30a2\u30eb\u30d0\u30e0", "\u30a2\u30a4\u30c9\u30ea\u30c3\u30b7\u30e5\u30bb\u30d6\u30f3", "\u5948\u7fa9", "\u5ca1\u5c71", "\u914d\u4ed8", "\u30d7\u30e9\u30a4\u30d9\u30c3\u30bf\u30fc", "\u5b9f\u73fe", "\u7f72\u540d", "\u3074\u3088\u308a\u3055\u3093"], "nega_count": 77, "posi_count": 477, "tweets_count": 2625, "retweets_count": 1476, "date": "2017/04/10"}, {"feature_words": ["\u30e9\u30b9\u30c8", "nd", "\u738b\u5b50", "\u5099\u3048\u4ed8\u3051", "VB", "\u30d0\u30ec", "\u60aa\u9b54", "\u7262\u7344", "prison", "\u30d1\u30eb\u30b3"], "nega_count": 75, "posi_count": 545, "tweets_count": 4255, "retweets_count": 2975, "date": "2017/04/09"}]