[{"nega_count": 92, "tweets_count": 7335, "date": "2017/12/24", "retweets_count": 5636, "posi_count": 702, "feature_words": ["merry", "\u30ed\u30fc\u30af\u30aa\u30ea\u30c6\u30a3\u30fc", "\u8a00\u3044\u8a33", "\u30d1\u30f3\u30c4\u30a1\u30fc\u30d5\u30a9\u30fc", "\u6628\u591c", "403", "\u30f4\u30a3\u30af\u30c8\u30eb", "\u30de\u30b9\u30bf\u30cb\u30e0", "\u3074\u3070", "christmas"]}, {"nega_count": 62, "tweets_count": 5021, "date": "2017/12/23", "retweets_count": 3814, "posi_count": 524, "feature_words": ["\u7948\u9858", "\u30a8\u30df\u30e4", "\u30bb\u30a4", "\u30ec\u30a2", "\u30ae\u30eb\u30ac\u30e1\u30c3\u30b7\u30e5", "\u30af\u30ea\u30a2", "93", "\u30d0\u30fc", "christmas", "happy"]}, {"nega_count": 52, "tweets_count": 7547, "date": "2017/12/22", "retweets_count": 6441, "posi_count": 437, "feature_words": ["\u7948\u9858", "\u30a8\u30df\u30e4", "\u30ec\u30a2", "\u30bb\u30a4", "\u30ae\u30eb\u30ac\u30e1\u30c3\u30b7\u30e5", "\u30af\u30ea\u30a2", "\u30d0\u30fc", "93", "\u667a\u7d75", "\u52a0\u5948"]}, {"nega_count": 73, "tweets_count": 3518, "date": "2017/12/21", "retweets_count": 2392, "posi_count": 463, "feature_words": ["\u8cac\u4efb", "\u6539\u61b2", "\u5b89\u500d", "\u30d7\u30e9\u30b9\u30bf\u30fc", "\u30ed\u30fc", "\u30bb\u30ac\u30b3\u30f3\u30c6\u30f3\u30c4\u30d7\u30ea\u30f3\u30c8", "\u518d\u73fe", "\u5bfe\u5cd9", "\u7d71\u4e00", "\u30bd\u30cb\u30c3\u30af"]}, {"nega_count": 57, "tweets_count": 3849, "date": "2017/12/20", "retweets_count": 2705, "posi_count": 470, "feature_words": ["\u30d4\u30af\u30b7\u30d6", "\u30b9\u30bf\u30c3\u30d5", "\u5bb6\u5ead", "\u30a2\u30eb\u30cd", "\u6587\u8c6a", "\u3046\u3058", "\u3057\u3087", "\u3060\u3044\u3058\u3087\u3046\u3076", "\u308c\u3044", "ENDLESS"]}, {"nega_count": 49, "tweets_count": 5005, "date": "2017/12/19", "retweets_count": 3917, "posi_count": 430, "feature_words": ["\u6587\u8c6a", "\u958b\u82b1", "\u9b45\u529b", "\u30b1\u30df\u30b9\u30c8", "\u30c0\u30fc\u30af", "\u576a\u5185", "\u6b63\u5b97", "\u30d4\u30af\u30b7\u30d6", "\u30b9\u30bf\u30c3\u30d5", "\u5bb6\u5ead"]}, {"nega_count": 51, "tweets_count": 3700, "date": "2017/12/18", "retweets_count": 2664, "posi_count": 431, "feature_words": ["\u30d5\u30a3\u30fc\u30ca", "\u30b0\u30e9\u30f3\u30c7\u30a3\u30a2", "\u30a2\u30a4\u30ab\u30c4\u30b9\u30bf\u30fc\u30ba", "\u30a2\u30a4\u30ab\u30c4", "\u6291\u6b62", "\u72af\u7f6a", "\uff11\u3064", "\u6cd5\u5f8b", "\u642c\u5165", "\u30f4\u30a7\u30eb\u30c6\u30a3"]}]