[{"retweets_count": 5059, "posi_count": 589, "tweets_count": 6476, "date": "2017/12/27", "nega_count": 87, "feature_words": ["\u4e88\u9632", "\u98df\u7269", "\u4e73\u5e7c\u5150", "\u5e30\u7701", "\u30e9\u30d9\u30eb", "\u7bc0\u7d04", "\u8cb4\u91cd", "\u58f2\u308a\u5b50", "\u30c4\u30fc\u30eb", "\u9023\u643a"]}, {"retweets_count": 5491, "posi_count": 708, "tweets_count": 7046, "date": "2017/12/26", "nega_count": 88, "feature_words": ["\u4e73\u5e7c\u5150", "\u98df\u7269", "\u4e88\u9632", "\u5e30\u7701", "\u30e9\u30d9\u30eb", "\u7bc0\u7d04", "\u58f2\u308a\u5b50", "\u30c4\u30fc\u30eb", "\u9023\u643a", "\u8cb4\u91cd"]}, {"retweets_count": 5139, "posi_count": 876, "tweets_count": 6989, "date": "2017/12/25", "nega_count": 95, "feature_words": ["\u30c1\u30a7\u30eb\u30af\u30a7\u30c3\u30c6\u30a3", "merry", "\u30ce\u30a8\u30eb", "mas", "\u30d1\u30b9", "\u30e9\u30d9\u30eb", "\u7bc0\u7d04", "\u30f4\u30a3\u30af\u30c8\u30eb", "\u30ad\u30e3\u30d3\u30cd\u30c3\u30c8", "\u9023\u643a"]}, {"retweets_count": 5636, "posi_count": 702, "tweets_count": 7335, "date": "2017/12/24", "nega_count": 92, "feature_words": ["merry", "\u30d1\u30f3\u30c4\u30a1\u30fc\u30d5\u30a9\u30fc", "\u8a00\u3044\u8a33", "\u30ed\u30fc\u30af\u30aa\u30ea\u30c6\u30a3\u30fc", "\u6628\u591c", "403", "\u30f4\u30a3\u30af\u30c8\u30eb", "\u3074\u3070", "\u30de\u30b9\u30bf\u30cb\u30e0", "christmas"]}, {"retweets_count": 3814, "posi_count": 524, "tweets_count": 5021, "date": "2017/12/23", "nega_count": 62, "feature_words": ["\u30c1\u30b3", "merry", "\u30a2\u30a4\u30c9\u30ea\u30c3\u30b7\u30e5\u30bb\u30d6\u30f3", "happy", "new", "christmas", "year", "\u6843\u674e", "\u30af\u30ea\u30b9\u30de\u30b9\u30c4\u30ea\u30fc", "\u30d7\u30c1"]}, {"retweets_count": 6441, "posi_count": 437, "tweets_count": 7547, "date": "2017/12/22", "nega_count": 52, "feature_words": ["\u30d0\u30ca\u30fc", "\u52a0\u5948", "\u667a\u7d75", "\u30b3\u30ec\u30c8", "\u5c0f\u677e\u539f", "\uff2e\uff2f", "\u5b89\u500d", "\u6539\u61b2", "\u30b7\u30ad\u30e8\u30af", "\u30aa\u30cb\u30aa\u30f3\u30d1\u30d1\u30b5\u30f3\u30bf"]}, {"retweets_count": 2392, "posi_count": 463, "tweets_count": 3518, "date": "2017/12/21", "nega_count": 73, "feature_words": ["\uff2e\uff2f", "\u6539\u61b2", "\u5b89\u500d", "\u30d0\u30ca\u30fc", "\u30d7\u30e9\u30b9\u30bf\u30fc", "\u30d4\u30f3\u30af", "\u7d71\u4e00", "\u30ed\u30fc", "\u30bb\u30ac\u30b3\u30f3\u30c6\u30f3\u30c4\u30d7\u30ea\u30f3\u30c8", "\u5bfe\u5cd9"]}]